README.rst
setup.py
difflibhelper/__init__.py
difflibhelper/difflibhelper.py
difflibhelper.egg-info/PKG-INFO
difflibhelper.egg-info/SOURCES.txt
difflibhelper.egg-info/dependency_links.txt
difflibhelper.egg-info/top_level.txt