Metadata-Version: 1.2
Name: difflibhelper
Version: 1.0.6
Summary: This script expands on the standard difflib library
Home-page: https://github.com/btr1975/difflibhelper
Author: Benjamin P. Trachtenberg
Author-email: e_ben_75-python@yahoo.com
License: MIT
Keywords: diff file differ differences
Platform: UNKNOWN
Classifier: Development Status :: 5 - Production/Stable
Classifier: Intended Audience :: Developers
Classifier: License :: OSI Approved :: MIT License
Classifier: Programming Language :: Python :: 3
Requires-Python: ~=3.3
